django_admin_smoke_tests-0.2.1.dist-info/DESCRIPTION.rst
django_admin_smoke_tests-0.2.1.dist-info/RECORD
django_admin_smoke_tests-0.2.1.dist-info/metadata.json
django_admin_smoke_tests-0.2.1.dist-info/WHEEL
django_admin_smoke_tests-0.2.1.dist-info/pbr.json
django_admin_smoke_tests-0.2.1.dist-info/METADATA
django_admin_smoke_tests-0.2.1.dist-info/top_level.txt
django_admin_smoke_tests/tests.py
django_admin_smoke_tests/__init__.py
